fp/__init__.py
fp/fp.py
free_proxy-1.0.2.dist-info/LICENSE
free_proxy-1.0.2.dist-info/METADATA
free_proxy-1.0.2.dist-info/WHEEL
free_proxy-1.0.2.dist-info/top_level.txt
free_proxy-1.0.2.dist-info/RECORD
