Metadata-Version: 2.1
Name: free-proxy
Version: 1.0.2
Summary: Proxy scraper for further use
Home-page: https://github.com/jundymek/free-proxy
Author: jundymek
Author-email: jundymek@gmail.com
License: UNKNOWN
Platform: UNKNOWN
Classifier: Programming Language :: Python :: 3
Classifier: License :: OSI Approved :: MIT License
Classifier: Operating System :: OS Independent
Requires-Python: >=3.6
